odoo/addons/l10n_es_aeat_mod303_oss/README.rst
odoo/addons/l10n_es_aeat_mod303_oss/__init__.py
odoo/addons/l10n_es_aeat_mod303_oss/__manifest__.py
odoo/addons/l10n_es_aeat_mod303_oss/data/2021-07/l10n_es_aeat_map_tax_line.xml
odoo/addons/l10n_es_aeat_mod303_oss/data/2023/l10n_es_aeat_map_tax_line.xml
odoo/addons/l10n_es_aeat_mod303_oss/i18n/l10n_es_aeat_mod303_oss.pot
odoo/addons/l10n_es_aeat_mod303_oss/models/__init__.py
odoo/addons/l10n_es_aeat_mod303_oss/models/mod303.py
odoo/addons/l10n_es_aeat_mod303_oss/readme/CONTRIBUTORS.rst
odoo/addons/l10n_es_aeat_mod303_oss/readme/DESCRIPTION.rst
odoo/addons/l10n_es_aeat_mod303_oss/static/description/icon.png
odoo/addons/l10n_es_aeat_mod303_oss/static/description/icon_source.svg
odoo/addons/l10n_es_aeat_mod303_oss/static/description/index.html
odoo/addons/l10n_es_aeat_mod303_oss/tests/__init__.py
odoo/addons/l10n_es_aeat_mod303_oss/tests/test_l10n_es_aeat_mod303_oss.py
odoo13_addon_l10n_es_aeat_mod303_oss-13.0.1.1.0.dist-info/METADATA
odoo13_addon_l10n_es_aeat_mod303_oss-13.0.1.1.0.dist-info/WHEEL
odoo13_addon_l10n_es_aeat_mod303_oss-13.0.1.1.0.dist-info/top_level.txt
odoo13_addon_l10n_es_aeat_mod303_oss-13.0.1.1.0.dist-info/RECORD
