Metadata-Version: 2.1
Name: odoo13-addon-l10n-es-aeat-mod303-oss
Version: 13.0.1.1.0
Summary: AEAT modelo 303 - OSS
Home-page: https://github.com/OCA/l10n-spain
Author: PESOL, Tecnativa, Odoo Community Association (OCA)
Author-email: support@odoo-community.org
License: AGPL-3
Platform: UNKNOWN
Classifier: Programming Language :: Python
Classifier: Framework :: Odoo
Classifier: Framework :: Odoo :: 13.0
Classifier: License :: OSI Approved :: GNU Affero General Public License v3
Requires-Python: >=3.5
Requires-Dist: odoo13-addon-l10n-es-aeat-mod303
Requires-Dist: odoo13-addon-l10n-eu-oss
Requires-Dist: odoo (<13.1dev,>=13.0a)
